gazeclassify/__init__.py
gazeclassify/facade.py
gazeclassify/facade_confidence.py
gazeclassify/facade_custom_algorithm.py
gazeclassify/facade_custom_loop.py
gazeclassify/facade_loop.py
gazeclassify/classifier/__init__.py
gazeclassify/classifier/instance.py
gazeclassify/classifier/semantic.py
gazeclassify/domain/__init__.py
gazeclassify/domain/classification.py
gazeclassify/domain/dataset.py
gazeclassify/domain/repository.py
gazeclassify/domain/results.py
gazeclassify/domain/serialization.py
gazeclassify/domain/video.py
gazeclassify/example_data/trial/gaze_positions.csv
gazeclassify/example_data/trial/world.mp4
gazeclassify/example_data/trial/world_timestamps.csv
gazeclassify/eyetracker/__init__.py
gazeclassify/eyetracker/csv_loader.py
gazeclassify/eyetracker/pupil.py
gazeclassify/service/__init__.py
gazeclassify/service/analysis.py
gazeclassify/service/deletion.py
gazeclassify/service/gaze_distance.py
gazeclassify/service/model_loader.py
gazeclassify/service/stats.py
gazeclassify/service/timestamp_matcher.py
gazeclassify/service/video.py
gazeclassify/tests/__init__.py
gazeclassify/tests/builder/__init__.py
gazeclassify/tests/builder/image_builder.py
gazeclassify/tests/builder/results_builder.py
gazeclassify/tests/system/__init__.py
gazeclassify/tests/system/test_InstanceSegmentation.py
gazeclassify/tests/system/test_SemanticSegmentation.py
gazeclassify/tests/unit/__init__.py
gazeclassify/tests/unit/test_ClassifierLoader.py
gazeclassify/tests/unit/test_CsvSerializer.py
gazeclassify/tests/unit/test_DistanceToMask.py
gazeclassify/tests/unit/test_Exceptions.py
gazeclassify/tests/unit/test_FileDeleter.py
gazeclassify/tests/unit/test_JsonSerializer.py
gazeclassify/tests/unit/test_OpenCVVideoReader.py
gazeclassify/tests/unit/test_PupilDataDeserializer.py
gazeclassify/tests/unit/test_PupilDataLoader.py
gazeclassify/tests/unit/test_PupilSerializer.py
gazeclassify/tests/unit/test_algorithm_confidence.py
gazeclassify/tests/unit/test_composite_video.py
gazeclassify-0.9.2.dist-info/LICENSE
gazeclassify-0.9.2.dist-info/METADATA
gazeclassify-0.9.2.dist-info/WHEEL
gazeclassify-0.9.2.dist-info/top_level.txt
gazeclassify-0.9.2.dist-info/RECORD
