Metadata-Version: 2.1
Name: gazeclassify
Version: 0.9.2
Summary: Algorithmic eye-tracking analysis
Home-page: https://github.com/footballdaniel/gazeclassify
Author: Daniel Müller
Author-email: daniel@science.football
Classifier: Intended Audience :: Developers
Classifier: Intended Audience :: Science/Research
Classifier: Programming Language :: Python :: 3
Classifier: Programming Language :: Python :: 3.7
Classifier: Programming Language :: Python :: 3.8
Classifier: License :: OSI Approved
Classifier: Topic :: Scientific/Engineering
Requires-Python: >=3.6
License-File: LICENSE
Requires-Dist: tensorflow (>=2.5.0)
Requires-Dist: ffmpeg-python (>=0.2.0)
Requires-Dist: opencv-python (>=4.1.2)
Requires-Dist: pixellib (>=0.6.6)
Requires-Dist: tqdm (>=4.60.0)
Requires-Dist: moviepy (>=1.0.3)
Requires-Dist: tabulate (>=0.8.9)
Requires-Dist: pandas (>=1.2.5)
